mdtranslator/__init__.py
mdtranslator/cli.py
mdtranslator/main.py
mdtranslator/translation.py
mdtranslator-0.1.1.dist-info/METADATA
mdtranslator-0.1.1.dist-info/WHEEL
mdtranslator-0.1.1.dist-info/entry_points.txt
mdtranslator-0.1.1.dist-info/top_level.txt
mdtranslator-0.1.1.dist-info/RECORD
