Metadata-Version: 2.4
Name: mdtranslator
Version: 0.1.1
Summary: Markdown 文件翻译 CLI（OpenAI/Anthropic/Google，代码块跳过，增量翻译，429 全局退避）
Author-email: ShiWu <xyz.liu15@gmail.com>
Project-URL: Homepage, https://github.com/xyz-liu15/mdtranslator
Project-URL: Source, https://github.com/xyz-liu15/mdtranslator
Project-URL: Issues, https://github.com/xyz-liu15/mdtranslator/issues
Keywords: markdown,translation,langchain,openai,anthropic,google,cli
Classifier: Programming Language :: Python :: 3
Classifier: License :: OSI Approved :: MIT License
Classifier: Environment :: Console
Classifier: Topic :: Text Processing :: Linguistic
Classifier: Topic :: Utilities
Classifier: Typing :: Typed
Requires-Python: >=3.9
Requires-Dist: aiofiles
Requires-Dist: rich>=13
Requires-Dist: PyYAML
Requires-Dist: langchain-core
Requires-Dist: build>=1.3.0
Requires-Dist: twine>=6.1.0
Provides-Extra: openai
Requires-Dist: langchain-openai; extra == "openai"
Provides-Extra: anthropic
Requires-Dist: langchain-anthropic; extra == "anthropic"
Provides-Extra: google
Requires-Dist: langchain-google-genai; extra == "google"
